diperion/__init__.py
diperion/common/__init__.py
diperion/common/exceptions.py
diperion/semantic_engine/__init__.py
diperion/semantic_engine/agent_proxy.py
diperion/semantic_engine/business_intelligence.py
diperion/semantic_engine/client.py
diperion/semantic_engine/config.py
diperion/semantic_engine/models.py
diperion-0.1.0.dist-info/licenses/LICENSE
diperion-0.1.0.dist-info/METADATA
diperion-0.1.0.dist-info/WHEEL
diperion-0.1.0.dist-info/top_level.txt
diperion-0.1.0.dist-info/RECORD
