Metadata-Version: 2.4
Name: diperion
Version: 0.1.0
Summary: Python SDK for the Diperion Semantic Engine - Build powerful semantic applications with ease
Home-page: https://github.com/diperion/diperion-python-sdk
Author: Diperion Team
Author-email: Diperion Team <contacto@diperion.com>
License: MIT
Project-URL: Homepage, https://diperion.com
Project-URL: Documentation, https://api.diperion.com/docs
Project-URL: Repository, https://github.com/diperion/diperion-python-sdk
Project-URL: Bug Tracker, https://github.com/diperion/diperion-python-sdk/issues
Project-URL: API Reference, https://api.diperion.com/health
Keywords: semantic,engine,graph,knowledge,ai,machine-learning,nlp,database,query,api,sdk,diperion,business-intelligence,semantic-search
Classifier: Development Status :: 4 - Beta
Classifier: Intended Audience :: Developers
Classifier: License :: OSI Approved :: MIT License
Classifier: Operating System :: OS Independent
Classifier: Programming Language :: Python :: 3
Classifier: Programming Language :: Python :: 3.8
Classifier: Programming Language :: Python :: 3.9
Classifier: Programming Language :: Python :: 3.10
Classifier: Programming Language :: Python :: 3.11
Classifier: Programming Language :: Python :: 3.12
Classifier: Topic :: Software Development :: Libraries :: Python Modules
Classifier: Topic :: Scientific/Engineering :: Artificial Intelligence
Classifier: Topic :: Database :: Database Engines/Servers
Requires-Python: >=3.8
License-File: LICENSE
Requires-Dist: requests>=2.25.0
Requires-Dist: typing-extensions>=4.0.0; python_version < "3.10"
Provides-Extra: dev
Requires-Dist: pytest>=7.0.0; extra == "dev"
Requires-Dist: pytest-cov>=4.0.0; extra == "dev"
Requires-Dist: black>=22.0.0; extra == "dev"
Requires-Dist: flake8>=4.0.0; extra == "dev"
Requires-Dist: mypy>=0.991; extra == "dev"
Requires-Dist: twine>=4.0.0; extra == "dev"
Requires-Dist: build>=0.8.0; extra == "dev"
Provides-Extra: docs
Requires-Dist: sphinx>=5.0.0; extra == "docs"
Requires-Dist: sphinx-rtd-theme>=1.0.0; extra == "docs"
Dynamic: author
Dynamic: home-page
Dynamic: license-file
Dynamic: requires-python
